{
  "date": "2026-06-01",
  "generated_at": "2026-06-01T13:04:31.031429",
  "run_mode": "late",
  "games": [
    {
      "away": "DET",
      "home": "TBR",
      "away_pitcher": "Ty Madden",
      "home_pitcher": "Griffin Jax",
      "model_home_wp": 0.6543,
      "model_away_wp": 0.3457,
      "avg_total_runs": 8.83,
      "elo_home_wp": 0.8105,
      "sim_home_wp": 0.498,
      "lineup_status": "projected",
      "home_lineup_names": [
        "Yandy D\u00edaz",
        "Jonathan Aranda",
        "Richie Palacios",
        "Junior Caminero",
        "Chandler Simpson",
        "Victor Mesa Jr.",
        "Cedric Mullins",
        "Hunter Feduccia",
        "Taylor Walls"
      ],
      "away_lineup_names": [
        "Colt Keith",
        "Kevin McGonigle",
        "Dillon Dingler",
        "Kerry Carpenter",
        "Riley Greene",
        "Spencer Torkelson",
        "Wenceel P\u00e9rez",
        "Matt Vierling",
        "Zach McKinstry"
      ],
      "sim_detail": {
        "avg_home_runs": 4.2,
        "avg_away_runs": 4.63,
        "std_total_runs": 4.23,
        "margin_distribution": {
          "labels": [
            -10,
            -9,
            -8,
            -7,
            -6,
            -5,
            -4,
            -3,
            -2,
            -1,
            0,
            1,
            2,
            3,
            4,
            5,
            6,
            7,
            8,
            9,
            10
          ],
          "freq": [
            0.6,
            0.9,
            1.6,
            2.3,
            3.9,
            4.7,
            6.2,
            8.3,
            10.5,
            12.5,
            0.0,
            14.5,
            10.0,
            7.6,
            5.3,
            3.5,
            2.2,
            1.5,
            1.0,
            0.7,
            0.3
          ]
        },
        "run_distribution": {
          "labels": [
            0,
            1,
            2,
            3,
            4,
            5,
            6,
            7,
            8,
            9,
            10,
            11,
            12,
            13,
            14,
            15
          ],
          "home_freq": [
            6.9,
            10.8,
            13.1,
            14.5,
            13.8,
            12.2,
            9.6,
            6.8,
            4.4,
            3.0,
            1.9,
            1.3,
            0.7,
            0.5,
            0.2,
            0.1
          ],
          "away_freq": [
            5.7,
            9.3,
            12.2,
            13.3,
            13.7,
            11.4,
            9.6,
            7.8,
            6.2,
            3.9,
            2.5,
            1.9,
            1.1,
            0.7,
            0.4,
            0.2
          ]
        }
      },
      "weather": {},
      "park_factors": {
        "runs": 1.0,
        "lhb_ba": 1.0,
        "rhb_ba": 0.94,
        "lhb_hr": 0.92,
        "rhb_hr": 1.08,
        "bb": 1.0,
        "k": 1.08,
        "HR": 1.0,
        "1B": 0.97,
        "2B": 1.0,
        "3B": 0.9
      },
      "elo_home_rating": 1546,
      "elo_away_rating": 1317,
      "market_home_wp": 0.6115,
      "market_away_wp": 0.3885,
      "books_home": {
        "fanduel": -178,
        "draftkings": -175,
        "williamhill_us": -170,
        "betmgm": -180,
        "bovada": -181
      },
      "books_away": {
        "fanduel": 150,
        "draftkings": 144,
        "williamhill_us": 143,
        "betmgm": 145,
        "bovada": 149
      },
      "confidence": 1.0
    },
    {
      "away": "MIA",
      "home": "WSN",
      "away_pitcher": "Sandy Alcantara",
      "home_pitcher": "Cade Cavalli",
      "model_home_wp": 0.614,
      "model_away_wp": 0.386,
      "avg_total_runs": 9.71,
      "elo_home_wp": 0.7207,
      "sim_home_wp": 0.5072,
      "lineup_status": "projected",
      "home_lineup_names": [
        "James Wood",
        "Luis Garc\u00eda Jr.",
        "Curtis Mead",
        "CJ Abrams",
        "Daylen Lile",
        "Jacob Young",
        "Jos\u00e9 Tena",
        "Drew Millas",
        "Nasim Nu\u00f1ez"
      ],
      "away_lineup_names": [
        "Xavier Edwards",
        "Liam Hicks",
        "Otto Lopez",
        "Kyle Stowers",
        "Jakob Marsee",
        "Connor Norby",
        "Owen Caissie",
        "Christopher Morel",
        "Joe Mack"
      ],
      "sim_detail": {
        "avg_home_runs": 4.66,
        "avg_away_runs": 5.05,
        "std_total_runs": 4.53,
        "margin_distribution": {
          "labels": [
            -10,
            -9,
            -8,
            -7,
            -6,
            -5,
            -4,
            -3,
            -2,
            -1,
            0,
            1,
            2,
            3,
            4,
            5,
            6,
            7,
            8,
            9,
            10
          ],
          "freq": [
            0.8,
            1.1,
            1.7,
            2.7,
            3.6,
            4.8,
            6.4,
            8.2,
            9.4,
            11.5,
            0.0,
            13.8,
            9.9,
            7.7,
            5.1,
            3.9,
            2.8,
            1.7,
            1.4,
            0.7,
            0.6
          ]
        },
        "run_distribution": {
          "labels": [
            0,
            1,
            2,
            3,
            4,
            5,
            6,
            7,
            8,
            9,
            10,
            11,
            12,
            13,
            14,
            15
          ],
          "home_freq": [
            5.0,
            9.0,
            12.0,
            14.0,
            13.7,
            11.7,
            10.2,
            7.8,
            5.8,
            3.8,
            2.6,
            2.0,
            1.1,
            0.6,
            0.3,
            0.2
          ],
          "away_freq": [
            4.8,
            8.2,
            11.5,
            11.5,
            12.2,
            11.8,
            10.7,
            8.3,
            6.7,
            4.5,
            3.3,
            2.3,
            1.7,
            1.1,
            0.6,
            0.4
          ]
        }
      },
      "weather": {},
      "park_factors": {
        "runs": 1.0,
        "lhb_ba": 1.0,
        "rhb_ba": 1.0,
        "lhb_hr": 0.95,
        "rhb_hr": 1.0,
        "bb": 0.95,
        "k": 0.95,
        "HR": 0.98,
        "1B": 1.0,
        "2B": 1.0,
        "3B": 1.0
      },
      "elo_home_rating": 1570,
      "elo_away_rating": 1429,
      "market_home_wp": 0.5657,
      "market_away_wp": 0.4343,
      "books_home": {
        "fanduel": -142,
        "draftkings": -144,
        "williamhill_us": -145,
        "betmgm": -145,
        "bovada": -144
      },
      "books_away": {
        "fanduel": 120,
        "draftkings": 119,
        "williamhill_us": 122,
        "betmgm": 120,
        "bovada": 121
      },
      "confidence": 1.0
    },
    {
      "away": "KCR",
      "home": "CIN",
      "away_pitcher": "Luinder Avila",
      "home_pitcher": "Chase Burns",
      "model_home_wp": 0.6201,
      "model_away_wp": 0.3799,
      "avg_total_runs": 10.23,
      "elo_home_wp": 0.7361,
      "sim_home_wp": 0.5042,
      "lineup_status": "projected",
      "home_lineup_names": [
        "Blake Dunn",
        "JJ Bleday",
        "Sal Stewart",
        "Eugenio Su\u00e1rez",
        "Nathaniel Lowe",
        "Spencer Steer",
        "Tyler Stephenson",
        "TJ Friedl",
        "Matt McLain"
      ],
      "away_lineup_names": [
        "Carter Jensen",
        "Bobby Witt Jr.",
        "Vinnie Pasquantino",
        "Salvador Perez",
        "Jac Caglianone",
        "Isaac Collins",
        "Michael Massey",
        "Nick Loftin",
        "Kyle Isbel"
      ],
      "sim_detail": {
        "avg_home_runs": 4.89,
        "avg_away_runs": 5.34,
        "std_total_runs": 4.65,
        "margin_distribution": {
          "labels": [
            -10,
            -9,
            -8,
            -7,
            -6,
            -5,
            -4,
            -3,
            -2,
            -1,
            0,
            1,
            2,
            3,
            4,
            5,
            6,
            7,
            8,
            9,
            10
          ],
          "freq": [
            1.1,
            1.2,
            2.0,
            2.4,
            3.4,
            4.7,
            6.4,
            8.2,
            9.5,
            11.6,
            0.0,
            13.7,
            10.0,
            7.6,
            5.3,
            3.8,
            2.9,
            1.6,
            1.3,
            0.7,
            0.6
          ]
        },
        "run_distribution": {
          "labels": [
            0,
            1,
            2,
            3,
            4,
            5,
            6,
            7,
            8,
            9,
            10,
            11,
            12,
            13,
            14,
            15
          ],
          "home_freq": [
            4.6,
            8.0,
            11.1,
            12.9,
            13.2,
            12.4,
            10.4,
            8.5,
            6.0,
            4.7,
            3.5,
            1.8,
            1.3,
            0.7,
            0.4,
            0.2
          ],
          "away_freq": [
            3.8,
            7.0,
            9.8,
            12.2,
            12.2,
            11.9,
            10.7,
            9.0,
            7.0,
            5.3,
            3.8,
            2.5,
            1.8,
            1.1,
            0.8,
            0.5
          ]
        }
      },
      "weather": {
        "temperature": 71.0,
        "wind_speed": 7.8,
        "wind_direction": "out",
        "condition": "Forecast"
      },
      "park_factors": {
        "runs": 1.05,
        "lhb_ba": 1.0,
        "rhb_ba": 1.0,
        "lhb_hr": 1.35,
        "rhb_hr": 1.26,
        "bb": 1.0,
        "k": 1.0,
        "HR": 1.31,
        "1B": 1.0,
        "2B": 1.05,
        "3B": 0.98
      },
      "elo_home_rating": 1499,
      "elo_away_rating": 1345,
      "market_home_wp": 0.6536,
      "market_away_wp": 0.3464,
      "books_home": {
        "fanduel": -198,
        "draftkings": -226,
        "williamhill_us": -220,
        "betmgm": -220,
        "bovada": -218
      },
      "books_away": {
        "fanduel": 166,
        "draftkings": 184,
        "williamhill_us": 180,
        "betmgm": 180,
        "bovada": 178
      },
      "confidence": 1.0
    },
    {
      "away": "CWS",
      "home": "MIN",
      "away_pitcher": "David Sandlin",
      "home_pitcher": "Joe Ryan",
      "model_home_wp": 0.4531,
      "model_away_wp": 0.5469,
      "avg_total_runs": 9.4,
      "elo_home_wp": 0.3833,
      "sim_home_wp": 0.523,
      "lineup_status": "projected",
      "home_lineup_names": [
        "Byron Buxton",
        "Brooks Lee",
        "Kody Clemens",
        "Josh Bell",
        "Trevor Larnach",
        "Austin Martin",
        "Victor Caratini",
        "Luke Keaschall",
        "Tristan Gray"
      ],
      "away_lineup_names": [
        "Sam Antonacci",
        "Miguel Vargas",
        "Andrew Benintendi",
        "Colson Montgomery",
        "Chase Meidroth",
        "Jacob Gonzalez",
        "Tristan Peters",
        "Drew Romo",
        "Rikuu Nishida"
      ],
      "sim_detail": {
        "avg_home_runs": 4.62,
        "avg_away_runs": 4.78,
        "std_total_runs": 4.45,
        "margin_distribution": {
          "labels": [
            -10,
            -9,
            -8,
            -7,
            -6,
            -5,
            -4,
            -3,
            -2,
            -1,
            0,
            1,
            2,
            3,
            4,
            5,
            6,
            7,
            8,
            9,
            10
          ],
          "freq": [
            0.7,
            1.0,
            1.6,
            2.4,
            3.3,
            4.2,
            6.0,
            8.0,
            9.6,
            12.3,
            0.0,
            13.5,
            11.0,
            8.3,
            5.2,
            3.8,
            2.7,
            1.7,
            1.4,
            0.8,
            0.6
          ]
        },
        "run_distribution": {
          "labels": [
            0,
            1,
            2,
            3,
            4,
            5,
            6,
            7,
            8,
            9,
            10,
            11,
            12,
            13,
            14,
            15
          ],
          "home_freq": [
            5.0,
            9.2,
            12.1,
            13.5,
            13.6,
            12.3,
            10.4,
            8.3,
            5.6,
            3.8,
            2.6,
            1.5,
            0.8,
            0.7,
            0.3,
            0.2
          ],
          "away_freq": [
            5.5,
            9.2,
            11.9,
            12.9,
            12.3,
            12.1,
            9.7,
            7.9,
            5.9,
            4.3,
            2.8,
            2.2,
            1.3,
            1.0,
            0.4,
            0.3
          ]
        }
      },
      "weather": {
        "temperature": 78.7,
        "wind_speed": 5.2,
        "wind_direction": "cross",
        "condition": "Forecast"
      },
      "park_factors": {
        "runs": 1.07,
        "lhb_ba": 1.0,
        "rhb_ba": 1.0,
        "lhb_hr": 1.0,
        "rhb_hr": 1.0,
        "bb": 1.06,
        "k": 1.0,
        "HR": 1.01,
        "1B": 1.0,
        "2B": 1.01,
        "3B": 0.91
      },
      "elo_home_rating": 1454,
      "elo_away_rating": 1560,
      "market_home_wp": 0.5922,
      "market_away_wp": 0.4078,
      "books_home": {
        "fanduel": -162,
        "draftkings": -163,
        "williamhill_us": -160,
        "betmgm": -165,
        "bovada": -162
      },
      "books_away": {
        "fanduel": 136,
        "draftkings": 135,
        "williamhill_us": 135,
        "betmgm": 135,
        "bovada": 136
      },
      "confidence": 0.722,
      "pick": "CWS ML",
      "edge_pct": 9.0,
      "odds": "+136",
      "kelly_fraction": 0.0323,
      "explanation": "Joe Ryan's surface line reads like an ace, but the underlying contact quality tells you he's been getting away with something for months. The White Sox are not a good team, yet they happen to roll out exactly the right-handed bats that have been barreling Ryan up all year, with Montgomery in particular fitting the profile of the hitter who eats this arm alive. Park is playing up, the ball is carrying, and the model has this as essentially a coin flip while the board is selling it as a Twins formality. At +136 on a dog whose lineup matches the starter's worst split, you take the price and let the variance do the work."
    },
    {
      "away": "SFG",
      "home": "MIL",
      "away_pitcher": "Landen Roupp",
      "home_pitcher": "Shane Drohan",
      "status": "lineups_pending",
      "lineup_status": "pending"
    },
    {
      "away": "TEX",
      "home": "STL",
      "away_pitcher": "Jacob deGrom",
      "home_pitcher": "Michael McGreevy",
      "model_home_wp": 0.5563,
      "model_away_wp": 0.4437,
      "avg_total_runs": 8.96,
      "elo_home_wp": 0.5876,
      "sim_home_wp": 0.5249,
      "lineup_status": "projected",
      "home_lineup_names": [
        "JJ Wetherholt",
        "Iv\u00e1n Herrera",
        "Alec Burleson",
        "Jordan Walker",
        "Nolan Gorman",
        "Masyn Winn",
        "Jimmy Crooks",
        "Bryan Torres",
        "Victor Scott II"
      ],
      "away_lineup_names": [
        "Joc Pederson",
        "Josh Jung",
        "Brandon Nimmo",
        "Jake Burger",
        "Evan Carter",
        "Ezequiel Duran",
        "Alejandro Osuna",
        "Danny Jansen",
        "Nicky Lopez"
      ],
      "sim_detail": {
        "avg_home_runs": 4.36,
        "avg_away_runs": 4.6,
        "std_total_runs": 4.36,
        "margin_distribution": {
          "labels": [
            -10,
            -9,
            -8,
            -7,
            -6,
            -5,
            -4,
            -3,
            -2,
            -1,
            0,
            1,
            2,
            3,
            4,
            5,
            6,
            7,
            8,
            9,
            10
          ],
          "freq": [
            0.7,
            1.0,
            1.5,
            2.0,
            3.2,
            4.8,
            6.0,
            7.9,
            9.8,
            11.8,
            0.0,
            15.4,
            10.7,
            7.5,
            4.9,
            4.2,
            2.4,
            1.9,
            1.1,
            0.8,
            0.4
          ]
        },
        "run_distribution": {
          "labels": [
            0,
            1,
            2,
            3,
            4,
            5,
            6,
            7,
            8,
            9,
            10,
            11,
            12,
            13,
            14,
            15
          ],
          "home_freq": [
            5.9,
            10.4,
            13.3,
            13.7,
            13.7,
            12.2,
            9.5,
            7.5,
            5.1,
            3.1,
            2.2,
            1.4,
            0.8,
            0.4,
            0.3,
            0.2
          ],
          "away_freq": [
            5.8,
            10.3,
            12.5,
            13.2,
            12.7,
            11.7,
            9.4,
            7.7,
            5.4,
            4.0,
            2.5,
            1.8,
            1.1,
            0.9,
            0.5,
            0.2
          ]
        }
      },
      "weather": {
        "temperature": 78.0,
        "wind_speed": 5.9,
        "wind_direction": "out",
        "condition": "Forecast"
      },
      "park_factors": {
        "runs": 1.0,
        "lhb_ba": 1.0,
        "rhb_ba": 1.0,
        "lhb_hr": 0.95,
        "rhb_hr": 0.82,
        "bb": 1.0,
        "k": 0.93,
        "HR": 0.9,
        "1B": 1.0,
        "2B": 1.02,
        "3B": 0.96
      },
      "elo_home_rating": 1501,
      "elo_away_rating": 1463,
      "market_home_wp": 0.466,
      "market_away_wp": 0.534,
      "books_home": {
        "fanduel": 106,
        "draftkings": 104,
        "williamhill_us": 105,
        "betmgm": 105,
        "bovada": 107
      },
      "books_away": {
        "fanduel": -124,
        "draftkings": -125,
        "williamhill_us": -125,
        "betmgm": -130,
        "bovada": -128
      },
      "confidence": 0.82,
      "pick": "STL ML",
      "edge_pct": 6.7,
      "odds": "+107",
      "kelly_fraction": 0.0239,
      "explanation": "Nobody wants to back the team facing deGrom, which is exactly why the price on the Cardinals got soft enough to matter. The market is treating this like a deGrom shutout instead of what it actually is, a coin flip the projection sees tilting slightly the other way. McGreevy isn't going to miss bats, but he doesn't need to against a Texas lineup that's been more name than production, and the Cardinals happen to carry a left-handed-leaning group that's punished deGrom's profile to the tune of a .291 xwOBA. Getting +107 on the better Elo team in a projected one-run game is the kind of math that doesn't care who's on the mound."
    },
    {
      "away": "COL",
      "home": "LAA",
      "away_pitcher": "Kyle Freeland",
      "home_pitcher": "Jose Soriano",
      "model_home_wp": 0.5534,
      "model_away_wp": 0.4466,
      "avg_total_runs": 8.81,
      "elo_home_wp": 0.5795,
      "sim_home_wp": 0.5272,
      "lineup_status": "projected",
      "home_lineup_names": [
        "Zach Neto",
        "Mike Trout",
        "Vaughn Grissom",
        "Jorge Soler",
        "Jo Adell",
        "Oswald Peraza",
        "Jose Siri",
        "Logan O'Hoppe",
        "Nick Madrigal"
      ],
      "away_lineup_names": [
        "Jake McCarthy",
        "Tyler Freeman",
        "Troy Johnston",
        "Hunter Goodman",
        "Willi Castro",
        "Ezequiel Tovar",
        "Sterlin Thompson",
        "Kyle Karros",
        "Edouard Julien"
      ],
      "sim_detail": {
        "avg_home_runs": 4.31,
        "avg_away_runs": 4.5,
        "std_total_runs": 4.27,
        "margin_distribution": {
          "labels": [
            -10,
            -9,
            -8,
            -7,
            -6,
            -5,
            -4,
            -3,
            -2,
            -1,
            0,
            1,
            2,
            3,
            4,
            5,
            6,
            7,
            8,
            9,
            10
          ],
          "freq": [
            0.7,
            1.2,
            1.6,
            2.4,
            2.9,
            4.4,
            5.7,
            8.0,
            9.3,
            12.5,
            0.0,
            14.7,
            10.7,
            7.8,
            5.8,
            3.9,
            2.8,
            1.8,
            1.1,
            0.8,
            0.3
          ]
        },
        "run_distribution": {
          "labels": [
            0,
            1,
            2,
            3,
            4,
            5,
            6,
            7,
            8,
            9,
            10,
            11,
            12,
            13,
            14,
            15
          ],
          "home_freq": [
            5.8,
            10.4,
            13.4,
            14.3,
            14.1,
            11.8,
            9.8,
            6.9,
            5.0,
            3.4,
            2.1,
            1.2,
            0.8,
            0.4,
            0.1,
            0.2
          ],
          "away_freq": [
            6.5,
            10.2,
            13.1,
            13.6,
            12.8,
            11.2,
            8.9,
            7.5,
            5.1,
            3.9,
            2.8,
            1.8,
            1.3,
            0.6,
            0.4,
            0.3
          ]
        }
      },
      "weather": {
        "temperature": 74.2,
        "wind_speed": 9.3,
        "wind_direction": "in",
        "condition": "Forecast"
      },
      "park_factors": {
        "runs": 1.0,
        "lhb_ba": 1.0,
        "rhb_ba": 0.94,
        "lhb_hr": 1.05,
        "rhb_hr": 1.07,
        "bb": 1.0,
        "k": 1.05,
        "HR": 1.06,
        "1B": 0.97,
        "2B": 1.0,
        "3B": 0.95
      },
      "elo_home_rating": 1406,
      "elo_away_rating": 1374,
      "market_home_wp": 0.6644,
      "market_away_wp": 0.3356,
      "books_home": {
        "fanduel": -225,
        "draftkings": -225,
        "williamhill_us": -220,
        "bovada": -225,
        "betmgm": -220
      },
      "books_away": {
        "fanduel": 188,
        "draftkings": 183,
        "williamhill_us": 180,
        "bovada": 185,
        "betmgm": 180
      },
      "confidence": 1.0,
      "pick": "COL ML",
      "edge_pct": 10.0,
      "odds": "+188",
      "kelly_fraction": 0.0338,
      "explanation": "Nobody wants to back Kyle Freeland on the road against a name-brand lineup, which is exactly why the Rockies are sitting at a price that implies they barely belong on the field. The problem with that math is Jose Soriano, who walks everybody he can't strike out and has been giving up loud contact to right-handed bats all season. Goodman is the exact profile that punishes a sinkerballer with an 11 percent walk rate, and the wind blowing in at 9 mph keeps Trout and Neto from doing their usual damage on the other side. The simulation has this as a coin flip the market is pricing as a 35 percent dog. +188 on a game that projects within a run is the entire argument."
    },
    {
      "away": "LAD",
      "home": "ARI",
      "away_pitcher": "Emmet Sheehan",
      "home_pitcher": "Eduardo Rodriguez",
      "model_home_wp": 0.4034,
      "model_away_wp": 0.5966,
      "avg_total_runs": 9.76,
      "elo_home_wp": 0.3356,
      "sim_home_wp": 0.4711,
      "lineup_status": "projected",
      "home_lineup_names": [
        "Ketel Marte",
        "Corbin Carroll",
        "Geraldo Perdomo",
        "Nolan Arenado",
        "Ryan Waldschmidt",
        "Adrian Del Castillo",
        "Gabriel Moreno",
        "Ildemaro Vargas",
        "Tommy Troy"
      ],
      "away_lineup_names": [
        "Shohei Ohtani",
        "Andy Pages",
        "Freddie Freeman",
        "Mookie Betts",
        "Kyle Tucker",
        "Will Smith",
        "Miguel Rojas",
        "Alex Call",
        "Santiago Espinal"
      ],
      "sim_detail": {
        "avg_home_runs": 4.5,
        "avg_away_runs": 5.26,
        "std_total_runs": 4.65,
        "margin_distribution": {
          "labels": [
            -10,
            -9,
            -8,
            -7,
            -6,
            -5,
            -4,
            -3,
            -2,
            -1,
            0,
            1,
            2,
            3,
            4,
            5,
            6,
            7,
            8,
            9,
            10
          ],
          "freq": [
            1.1,
            1.4,
            2.1,
            3.0,
            4.0,
            5.1,
            6.3,
            7.9,
            10.4,
            12.0,
            0.0,
            13.2,
            9.9,
            6.8,
            4.7,
            3.5,
            2.4,
            1.5,
            1.1,
            0.6,
            0.4
          ]
        },
        "run_distribution": {
          "labels": [
            0,
            1,
            2,
            3,
            4,
            5,
            6,
            7,
            8,
            9,
            10,
            11,
            12,
            13,
            14,
            15
          ],
          "home_freq": [
            5.9,
            10.0,
            12.6,
            13.7,
            13.0,
            12.4,
            9.3,
            7.5,
            5.3,
            4.0,
            2.3,
            1.5,
            1.0,
            0.5,
            0.3,
            0.3
          ],
          "away_freq": [
            4.3,
            8.1,
            10.0,
            11.4,
            12.6,
            11.3,
            10.4,
            8.6,
            6.9,
            4.8,
            4.0,
            2.7,
            1.6,
            1.4,
            0.7,
            0.4
          ]
        }
      },
      "weather": {
        "condition": "Roof Closed"
      },
      "park_factors": {
        "runs": 1.0,
        "lhb_ba": 1.0,
        "rhb_ba": 1.0,
        "lhb_hr": 0.72,
        "rhb_hr": 0.87,
        "bb": 1.0,
        "k": 1.0,
        "HR": 0.8,
        "1B": 1.01,
        "2B": 1.02,
        "3B": 0.95
      },
      "elo_home_rating": 1526,
      "elo_away_rating": 1669,
      "market_home_wp": 0.4118,
      "market_away_wp": 0.5882,
      "books_home": {
        "fanduel": 134,
        "draftkings": 130,
        "williamhill_us": 135,
        "betmgm": 135,
        "bovada": 130
      },
      "books_away": {
        "fanduel": -158,
        "draftkings": -157,
        "williamhill_us": -160,
        "betmgm": -165,
        "bovada": -155
      },
      "confidence": 1.0
    },
    {
      "away": "NYM",
      "home": "SEA",
      "away_pitcher": "Austin Warren",
      "home_pitcher": "Emerson Hancock",
      "model_home_wp": 0.574,
      "model_away_wp": 0.426,
      "avg_total_runs": 7.48,
      "elo_home_wp": 0.6469,
      "sim_home_wp": 0.5012,
      "lineup_status": "projected",
      "home_lineup_names": [
        "J.P. Crawford",
        "Julio Rodr\u00edguez",
        "Josh Naylor",
        "Randy Arozarena",
        "Rob Refsnyder",
        "Victor Robles",
        "Cole Young",
        "Mitch Garver",
        "Colt Emerson"
      ],
      "away_lineup_names": [
        "Carson Benge",
        "Bo Bichette",
        "Juan Soto",
        "Jared Young",
        "Mark Vientos",
        "A.J. Ewing",
        "Brett Baty",
        "Marcus Semien",
        "Luis Torrens"
      ],
      "sim_detail": {
        "avg_home_runs": 3.56,
        "avg_away_runs": 3.92,
        "std_total_runs": 3.85,
        "margin_distribution": {
          "labels": [
            -10,
            -9,
            -8,
            -7,
            -6,
            -5,
            -4,
            -3,
            -2,
            -1,
            0,
            1,
            2,
            3,
            4,
            5,
            6,
            7,
            8,
            9,
            10
          ],
          "freq": [
            0.4,
            0.8,
            1.3,
            2.0,
            3.2,
            4.4,
            6.4,
            8.2,
            10.9,
            14.1,
            0.0,
            15.9,
            10.9,
            7.6,
            4.8,
            3.0,
            2.1,
            1.3,
            0.8,
            0.6,
            0.2
          ]
        },
        "run_distribution": {
          "labels": [
            0,
            1,
            2,
            3,
            4,
            5,
            6,
            7,
            8,
            9,
            10,
            11,
            12,
            13,
            14,
            15
          ],
          "home_freq": [
            10.5,
            13.6,
            15.2,
            15.3,
            14.1,
            10.4,
            7.4,
            5.4,
            3.1,
            2.2,
            1.2,
            0.8,
            0.4,
            0.2,
            0.1,
            0.1
          ],
          "away_freq": [
            8.3,
            12.0,
            14.7,
            15.2,
            12.7,
            11.7,
            8.7,
            6.5,
            3.8,
            2.5,
            1.8,
            0.9,
            0.5,
            0.4,
            0.2,
            0.1
          ]
        }
      },
      "weather": {
        "condition": "Roof Closed"
      },
      "park_factors": {
        "runs": 0.83,
        "lhb_ba": 0.91,
        "rhb_ba": 0.86,
        "lhb_hr": 0.85,
        "rhb_hr": 0.88,
        "bb": 1.0,
        "k": 1.14,
        "HR": 0.87,
        "1B": 0.88,
        "2B": 0.9,
        "3B": 0.95
      },
      "elo_home_rating": 1567,
      "elo_away_rating": 1486,
      "market_home_wp": 0.5643,
      "market_away_wp": 0.4357,
      "books_home": {
        "fanduel": -142,
        "williamhill_us": -140,
        "betmgm": -145,
        "draftkings": -143,
        "bovada": -145
      },
      "books_away": {
        "fanduel": 120,
        "williamhill_us": 118,
        "betmgm": 118,
        "draftkings": 119,
        "bovada": 122
      },
      "confidence": 1.0
    }
  ],
  "picks": [
    {
      "pick": "DET +1.5",
      "side": "away",
      "team": "DET",
      "opponent": "TBR",
      "edge_pct": 10.2,
      "model_prob": 0.672,
      "confidence": 1.0,
      "odds": "-135",
      "kelly_fraction": 0.05,
      "wager": 2612.25,
      "explanation": "Tampa is the better team and the price reflects that, but a run and a half is a lot of cushion to give a Detroit lineup built to do exactly what Jax struggles to suppress. The right-hander runs an elite strikeout rate, but lefties have tagged him for a .314 xwOBA and a hard-hit profile that says the contact he allows is the dangerous kind. Carpenter, Keith, and a Dingler bat that lights up against this exact handedness profile give the Tigers enough left-handed thunder to keep this within shouting distance even in a loss. At -135 you're not betting Detroit to win, you're betting the game stays close, and the sim has it landing inside a run.",
      "type": "run_line",
      "sportsbook_odds": {
        "fanduel": -144,
        "draftkings": -143,
        "williamhill_us": -135,
        "betmgm": -145,
        "bovada": -140
      },
      "lineup_status": "projected"
    },
    {
      "pick": "KCR +1.5",
      "side": "away",
      "team": "KCR",
      "opponent": "CIN",
      "edge_pct": 13.5,
      "model_prob": 0.657,
      "confidence": 1.0,
      "odds": "-108",
      "kelly_fraction": 0.05,
      "wager": 2612.25,
      "explanation": "Chase Burns has a strikeout number that makes him look like a problem until you notice which side of the plate is doing the damage, and Kansas City happens to roll out a lineup full of left-handed bats built to exploit exactly that hole. Burns has been getting tagged for a .383 wOBA by lefties with a walk rate that balloons into the double digits, which is the worst possible profile to bring into a Cincinnati bandbox with the wind blowing out. Meanwhile Luinder Avila has been quietly stingy in his small sample, and a Reds order leaning on Dunn and Bleday isn't the group that punishes a young arm into submission. Getting plus money on a run and a half, in a game our sim sees as a near coin flip on the moneyline, is the kind of price the board hands out when it's anchored to team names instead of the matchup underneath.",
      "type": "run_line",
      "sportsbook_odds": {
        "fanduel": -118,
        "draftkings": -108,
        "williamhill_us": -110,
        "betmgm": -110,
        "bovada": -115
      },
      "lineup_status": "projected"
    },
    {
      "pick": "CWS ML",
      "side": "away",
      "team": "CWS",
      "opponent": "MIN",
      "edge_pct": 9.0,
      "model_prob": 0.547,
      "confidence": 0.722,
      "odds": "+136",
      "kelly_fraction": 0.0323,
      "wager": 1686.48,
      "explanation": "Joe Ryan's surface line reads like an ace, but the underlying contact quality tells you he's been getting away with something for months. The White Sox are not a good team, yet they happen to roll out exactly the right-handed bats that have been barreling Ryan up all year, with Montgomery in particular fitting the profile of the hitter who eats this arm alive. Park is playing up, the ball is carrying, and the model has this as essentially a coin flip while the board is selling it as a Twins formality. At +136 on a dog whose lineup matches the starter's worst split, you take the price and let the variance do the work.",
      "type": "moneyline",
      "sportsbook_odds": {
        "fanduel": 136,
        "draftkings": 135,
        "williamhill_us": 135,
        "betmgm": 135,
        "bovada": 136
      },
      "lineup_status": "projected"
    },
    {
      "pick": "STL ML",
      "side": "home",
      "team": "STL",
      "opponent": "TEX",
      "edge_pct": 6.7,
      "model_prob": 0.556,
      "confidence": 0.82,
      "odds": "+107",
      "kelly_fraction": 0.0239,
      "wager": 1250.21,
      "explanation": "Nobody wants to back the team facing deGrom, which is exactly why the price on the Cardinals got soft enough to matter. The market is treating this like a deGrom shutout instead of what it actually is, a coin flip the projection sees tilting slightly the other way. McGreevy isn't going to miss bats, but he doesn't need to against a Texas lineup that's been more name than production, and the Cardinals happen to carry a left-handed-leaning group that's punished deGrom's profile to the tune of a .291 xwOBA. Getting +107 on the better Elo team in a projected one-run game is the kind of math that doesn't care who's on the mound.",
      "type": "moneyline",
      "sportsbook_odds": {
        "fanduel": 106,
        "draftkings": 104,
        "williamhill_us": 105,
        "betmgm": 105,
        "bovada": 107
      },
      "lineup_status": "projected"
    },
    {
      "pick": "COL ML",
      "side": "away",
      "team": "COL",
      "opponent": "LAA",
      "edge_pct": 10.0,
      "model_prob": 0.447,
      "confidence": 1.0,
      "odds": "+188",
      "kelly_fraction": 0.0338,
      "wager": 1766.89,
      "explanation": "Nobody wants to back Kyle Freeland on the road against a name-brand lineup, which is exactly why the Rockies are sitting at a price that implies they barely belong on the field. The problem with that math is Jose Soriano, who walks everybody he can't strike out and has been giving up loud contact to right-handed bats all season. Goodman is the exact profile that punishes a sinkerballer with an 11 percent walk rate, and the wind blowing in at 9 mph keeps Trout and Neto from doing their usual damage on the other side. The simulation has this as a coin flip the market is pricing as a 35 percent dog. +188 on a game that projects within a run is the entire argument.",
      "type": "moneyline",
      "sportsbook_odds": {
        "fanduel": 188,
        "draftkings": 183,
        "williamhill_us": 180,
        "bovada": 185,
        "betmgm": 180
      },
      "lineup_status": "projected"
    },
    {
      "pick": "COL +1.5",
      "side": "away",
      "team": "COL",
      "opponent": "LAA",
      "edge_pct": 12.5,
      "model_prob": 0.645,
      "confidence": 1.0,
      "odds": "-110",
      "kelly_fraction": 0.05,
      "wager": 2612.25,
      "explanation": "The market is pricing the Rockies like a doormat, which is fair most nights but ignores that Jose Soriano walks the ballpark and Colorado's lineup only needs to keep this within a run to cash. Soriano's 11.4% walk rate is the kind of command profile that turns a projected blowout into a four-hour slog, and the wind blowing in takes the easy escape hatch (a Trout swing, a Neto barrel) off the table. Freeland is not going to dazzle anyone, but our sim lands on a 4.5 to 4.3 game because the Angels can't separate when the opposing starter is putting himself in 2-0 counts. Getting a hook and a half at a plus-money adjacent number on a coin-flip game is the entire ballgame.",
      "type": "run_line",
      "sportsbook_odds": {
        "fanduel": -114,
        "draftkings": -114,
        "williamhill_us": -110,
        "bovada": -115,
        "betmgm": -110
      },
      "lineup_status": "projected"
    }
  ],
  "bankroll": {
    "current": 52245.08,
    "today_wagered": 12540.33
  }
}