{
  "date": "2026-06-03",
  "generated_at": "2026-06-03T10:37:19.339640",
  "run_mode": "late",
  "games": [
    {
      "away": "MIA",
      "home": "WSN",
      "away_pitcher": "Max Meyer",
      "home_pitcher": "Andrew Alvarez",
      "model_home_wp": 0.5603,
      "model_away_wp": 0.4397,
      "avg_total_runs": 9.37,
      "elo_home_wp": 0.5823,
      "sim_home_wp": 0.5383,
      "lineup_status": "projected",
      "home_lineup_names": [
        "James Wood",
        "Luis Garc\u00eda Jr.",
        "Curtis Mead",
        "CJ Abrams",
        "Daylen Lile",
        "Jacob Young",
        "Jos\u00e9 Tena",
        "Drew Millas",
        "Nasim Nu\u00f1ez"
      ],
      "away_lineup_names": [
        "Xavier Edwards",
        "Otto Lopez",
        "Heriberto Hern\u00e1ndez",
        "Christopher Morel",
        "Esteury Ruiz",
        "Liam Hicks",
        "Jakob Marsee",
        "Leo Jim\u00e9nez",
        "Joe Mack"
      ],
      "sim_detail": {
        "avg_home_runs": 4.65,
        "avg_away_runs": 4.72,
        "std_total_runs": 4.42,
        "margin_distribution": {
          "labels": [
            -10,
            -9,
            -8,
            -7,
            -6,
            -5,
            -4,
            -3,
            -2,
            -1,
            0,
            1,
            2,
            3,
            4,
            5,
            6,
            7,
            8,
            9,
            10
          ],
          "freq": [
            0.6,
            1.0,
            1.6,
            2.4,
            3.0,
            4.4,
            5.9,
            7.4,
            9.3,
            12.0,
            0.0,
            14.6,
            10.6,
            7.7,
            5.7,
            4.1,
            3.0,
            2.1,
            1.5,
            0.7,
            0.6
          ]
        },
        "run_distribution": {
          "labels": [
            0,
            1,
            2,
            3,
            4,
            5,
            6,
            7,
            8,
            9,
            10,
            11,
            12,
            13,
            14,
            15
          ],
          "home_freq": [
            4.9,
            9.4,
            12.2,
            13.3,
            12.9,
            12.3,
            10.3,
            7.9,
            5.9,
            4.0,
            2.5,
            1.7,
            1.2,
            0.7,
            0.2,
            0.2
          ],
          "away_freq": [
            5.9,
            9.0,
            11.9,
            13.0,
            12.7,
            11.7,
            10.0,
            8.1,
            5.7,
            4.1,
            2.9,
            2.1,
            1.0,
            0.8,
            0.5,
            0.4
          ]
        }
      },
      "weather": {},
      "park_factors": {
        "runs": 1.0,
        "lhb_ba": 1.0,
        "rhb_ba": 1.0,
        "lhb_hr": 0.95,
        "rhb_hr": 1.0,
        "bb": 0.95,
        "k": 0.95,
        "HR": 0.98,
        "1B": 1.0,
        "2B": 1.0,
        "3B": 1.0
      },
      "elo_home_rating": 1516,
      "elo_away_rating": 1483,
      "market_home_wp": 0.5,
      "market_away_wp": 0.5,
      "books_home": {
        "fanduel": -108,
        "draftkings": -110,
        "williamhill_us": -110,
        "bovada": -110,
        "betmgm": -110
      },
      "books_away": {
        "fanduel": -108,
        "draftkings": -110,
        "williamhill_us": -110,
        "bovada": -110,
        "betmgm": -110
      },
      "confidence": 1.0
    },
    {
      "away": "DET",
      "home": "TBR",
      "away_pitcher": "Troy Melton",
      "home_pitcher": "Nick Martinez",
      "model_home_wp": 0.5891,
      "model_away_wp": 0.4109,
      "avg_total_runs": 8.59,
      "elo_home_wp": 0.6793,
      "sim_home_wp": 0.4989,
      "lineup_status": "projected",
      "home_lineup_names": [
        "Chandler Simpson",
        "Junior Caminero",
        "Jonathan Aranda",
        "Yandy D\u00edaz",
        "Richie Palacios",
        "Victor Mesa Jr.",
        "Cedric Mullins",
        "Nick Fortes",
        "Taylor Walls"
      ],
      "away_lineup_names": [
        "Kevin McGonigle",
        "Gleyber Torres",
        "Kerry Carpenter",
        "Dillon Dingler",
        "Riley Greene",
        "Spencer Torkelson",
        "Colt Keith",
        "Wenceel P\u00e9rez",
        "Jake Rogers"
      ],
      "sim_detail": {
        "avg_home_runs": 4.1,
        "avg_away_runs": 4.49,
        "std_total_runs": 4.18,
        "margin_distribution": {
          "labels": [
            -10,
            -9,
            -8,
            -7,
            -6,
            -5,
            -4,
            -3,
            -2,
            -1,
            0,
            1,
            2,
            3,
            4,
            5,
            6,
            7,
            8,
            9,
            10
          ],
          "freq": [
            0.6,
            1.2,
            1.5,
            2.4,
            3.1,
            4.6,
            6.7,
            8.7,
            10.1,
            12.8,
            0.0,
            14.4,
            10.8,
            7.2,
            4.9,
            3.3,
            2.5,
            1.7,
            0.9,
            0.5,
            0.5
          ]
        },
        "run_distribution": {
          "labels": [
            0,
            1,
            2,
            3,
            4,
            5,
            6,
            7,
            8,
            9,
            10,
            11,
            12,
            13,
            14,
            15
          ],
          "home_freq": [
            7.2,
            11.6,
            13.6,
            14.7,
            13.9,
            11.2,
            9.2,
            6.7,
            4.4,
            3.0,
            2.0,
            1.1,
            0.6,
            0.3,
            0.2,
            0.1
          ],
          "away_freq": [
            5.7,
            9.7,
            13.2,
            13.8,
            13.6,
            11.7,
            9.5,
            7.5,
            5.5,
            3.4,
            2.4,
            1.6,
            1.0,
            0.6,
            0.3,
            0.2
          ]
        }
      },
      "weather": {},
      "park_factors": {
        "runs": 1.0,
        "lhb_ba": 1.0,
        "rhb_ba": 0.94,
        "lhb_hr": 0.92,
        "rhb_hr": 1.08,
        "bb": 1.0,
        "k": 1.08,
        "HR": 1.0,
        "1B": 0.97,
        "2B": 1.0,
        "3B": 0.9
      },
      "elo_home_rating": 1485,
      "elo_away_rating": 1378,
      "market_home_wp": 0.5704,
      "market_away_wp": 0.4296,
      "books_home": {
        "fanduel": -144,
        "draftkings": -149,
        "williamhill_us": -145,
        "bovada": -144,
        "betmgm": -150
      },
      "books_away": {
        "fanduel": 122,
        "draftkings": 123,
        "williamhill_us": 122,
        "bovada": 121,
        "betmgm": 125
      },
      "confidence": 1.0
    },
    {
      "away": "CWS",
      "home": "MIN",
      "away_pitcher": "Erick Fedde",
      "home_pitcher": "Taj Bradley",
      "model_home_wp": 0.5214,
      "model_away_wp": 0.4786,
      "avg_total_runs": 9.48,
      "elo_home_wp": 0.5116,
      "sim_home_wp": 0.5312,
      "lineup_status": "projected",
      "home_lineup_names": [
        "Byron Buxton",
        "Brooks Lee",
        "Kody Clemens",
        "Josh Bell",
        "Trevor Larnach",
        "Austin Martin",
        "Victor Caratini",
        "Luke Keaschall",
        "Tristan Gray"
      ],
      "away_lineup_names": [
        "Sam Antonacci",
        "Miguel Vargas",
        "Andrew Benintendi",
        "Colson Montgomery",
        "Chase Meidroth",
        "Jacob Gonzalez",
        "Tristan Peters",
        "Drew Romo",
        "Rikuu Nishida"
      ],
      "sim_detail": {
        "avg_home_runs": 4.64,
        "avg_away_runs": 4.84,
        "std_total_runs": 4.47,
        "margin_distribution": {
          "labels": [
            -10,
            -9,
            -8,
            -7,
            -6,
            -5,
            -4,
            -3,
            -2,
            -1,
            0,
            1,
            2,
            3,
            4,
            5,
            6,
            7,
            8,
            9,
            10
          ],
          "freq": [
            0.8,
            1.3,
            1.5,
            2.1,
            3.3,
            4.5,
            5.8,
            7.9,
            9.0,
            11.7,
            0.0,
            14.1,
            11.1,
            7.6,
            5.8,
            4.4,
            2.6,
            1.8,
            1.1,
            1.0,
            0.4
          ]
        },
        "run_distribution": {
          "labels": [
            0,
            1,
            2,
            3,
            4,
            5,
            6,
            7,
            8,
            9,
            10,
            11,
            12,
            13,
            14,
            15
          ],
          "home_freq": [
            5.2,
            8.7,
            12.1,
            13.5,
            13.4,
            12.4,
            10.3,
            8.3,
            5.8,
            4.0,
            2.3,
            1.6,
            1.1,
            0.6,
            0.4,
            0.2
          ],
          "away_freq": [
            5.5,
            8.9,
            11.4,
            13.4,
            12.2,
            11.9,
            9.7,
            7.9,
            5.8,
            4.1,
            3.3,
            2.4,
            1.2,
            0.9,
            0.6,
            0.4
          ]
        }
      },
      "weather": {
        "temperature": 83.8,
        "wind_speed": 11.5,
        "wind_direction": "out",
        "condition": "Forecast"
      },
      "park_factors": {
        "runs": 1.07,
        "lhb_ba": 1.0,
        "rhb_ba": 1.0,
        "lhb_hr": 1.0,
        "rhb_hr": 1.0,
        "bb": 1.06,
        "k": 1.0,
        "HR": 1.02,
        "1B": 1.0,
        "2B": 1.02,
        "3B": 0.92
      },
      "elo_home_rating": 1499,
      "elo_away_rating": 1515,
      "market_home_wp": 0.5876,
      "market_away_wp": 0.4124,
      "books_home": {
        "fanduel": -154,
        "draftkings": -156,
        "williamhill_us": -160,
        "bovada": -157,
        "betmgm": -160
      },
      "books_away": {
        "fanduel": 130,
        "draftkings": 129,
        "williamhill_us": 135,
        "bovada": 131,
        "betmgm": 135
      },
      "confidence": 1.0
    },
    {
      "away": "NYM",
      "home": "SEA",
      "away_pitcher": "Freddy Peralta",
      "home_pitcher": "George Kirby",
      "model_home_wp": 0.6107,
      "model_away_wp": 0.3893,
      "avg_total_runs": 7.49,
      "elo_home_wp": 0.7123,
      "sim_home_wp": 0.5092,
      "lineup_status": "projected",
      "home_lineup_names": [
        "J.P. Crawford",
        "Julio Rodr\u00edguez",
        "Josh Naylor",
        "Randy Arozarena",
        "Luke Raley",
        "Cole Young",
        "Dominic Canzone",
        "Mitch Garver",
        "Colt Emerson"
      ],
      "away_lineup_names": [
        "Carson Benge",
        "Bo Bichette",
        "Juan Soto",
        "Jared Young",
        "Mark Vientos",
        "Brett Baty",
        "Marcus Semien",
        "A.J. Ewing",
        "Luis Torrens"
      ],
      "sim_detail": {
        "avg_home_runs": 3.57,
        "avg_away_runs": 3.91,
        "std_total_runs": 3.86,
        "margin_distribution": {
          "labels": [
            -10,
            -9,
            -8,
            -7,
            -6,
            -5,
            -4,
            -3,
            -2,
            -1,
            0,
            1,
            2,
            3,
            4,
            5,
            6,
            7,
            8,
            9,
            10
          ],
          "freq": [
            0.5,
            0.8,
            1.3,
            2.0,
            3.1,
            4.2,
            5.9,
            8.6,
            10.5,
            14.0,
            0.0,
            16.0,
            11.7,
            7.5,
            4.9,
            3.2,
            2.2,
            1.3,
            0.7,
            0.4,
            0.3
          ]
        },
        "run_distribution": {
          "labels": [
            0,
            1,
            2,
            3,
            4,
            5,
            6,
            7,
            8,
            9,
            10,
            11,
            12,
            13,
            14,
            15
          ],
          "home_freq": [
            9.4,
            13.6,
            15.7,
            16.1,
            13.6,
            10.6,
            7.8,
            5.4,
            3.1,
            2.0,
            1.4,
            0.6,
            0.2,
            0.2,
            0.1,
            0.0
          ],
          "away_freq": [
            8.1,
            12.8,
            15.2,
            14.7,
            13.2,
            10.1,
            8.7,
            6.0,
            4.2,
            2.9,
            1.5,
            1.2,
            0.7,
            0.4,
            0.2,
            0.1
          ]
        }
      },
      "weather": {
        "condition": "Roof Closed"
      },
      "park_factors": {
        "runs": 0.83,
        "lhb_ba": 0.91,
        "rhb_ba": 0.86,
        "lhb_hr": 0.85,
        "rhb_hr": 0.88,
        "bb": 1.0,
        "k": 1.14,
        "HR": 0.87,
        "1B": 0.88,
        "2B": 0.9,
        "3B": 0.95
      },
      "elo_home_rating": 1593,
      "elo_away_rating": 1459,
      "market_home_wp": 0.569,
      "market_away_wp": 0.431,
      "books_home": {
        "fanduel": -142,
        "draftkings": -149,
        "williamhill_us": -145,
        "bovada": -142,
        "betmgm": -150
      },
      "books_away": {
        "fanduel": 120,
        "draftkings": 123,
        "williamhill_us": 122,
        "bovada": 119,
        "betmgm": 125
      },
      "confidence": 1.0
    },
    {
      "away": "SDP",
      "home": "PHI",
      "away_pitcher": "Walker Buehler",
      "home_pitcher": "Cristopher Sanchez",
      "model_home_wp": 0.6151,
      "model_away_wp": 0.3849,
      "avg_total_runs": 10.7,
      "elo_home_wp": 0.6762,
      "sim_home_wp": 0.5541,
      "lineup_status": "projected",
      "home_lineup_names": [
        "Kyle Schwarber",
        "Trea Turner",
        "Bryce Harper",
        "Brandon Marsh",
        "Alec Bohm",
        "Bryson Stott",
        "J.T. Realmuto",
        "Adolis Garc\u00eda",
        "Justin Crawford"
      ],
      "away_lineup_names": [
        "Fernando Tatis Jr.",
        "Miguel Andujar",
        "Manny Machado",
        "Xander Bogaerts",
        "Jackson Merrill",
        "Jase Bowen",
        "Ty France",
        "Nick Castellanos",
        "Rodolfo Dur\u00e1n"
      ],
      "sim_detail": {
        "avg_home_runs": 5.42,
        "avg_away_runs": 5.28,
        "std_total_runs": 4.78,
        "margin_distribution": {
          "labels": [
            -10,
            -9,
            -8,
            -7,
            -6,
            -5,
            -4,
            -3,
            -2,
            -1,
            0,
            1,
            2,
            3,
            4,
            5,
            6,
            7,
            8,
            9,
            10
          ],
          "freq": [
            0.9,
            1.2,
            1.7,
            2.6,
            3.0,
            4.5,
            5.6,
            6.7,
            9.0,
            10.9,
            0.0,
            13.6,
            10.4,
            7.5,
            6.3,
            4.5,
            3.5,
            2.3,
            1.6,
            1.1,
            0.8
          ]
        },
        "run_distribution": {
          "labels": [
            0,
            1,
            2,
            3,
            4,
            5,
            6,
            7,
            8,
            9,
            10,
            11,
            12,
            13,
            14,
            15
          ],
          "home_freq": [
            3.1,
            6.7,
            9.7,
            11.6,
            12.7,
            12.2,
            10.9,
            9.0,
            7.2,
            5.7,
            3.8,
            2.8,
            1.6,
            1.2,
            0.7,
            0.4
          ],
          "away_freq": [
            3.8,
            7.6,
            10.5,
            11.7,
            11.8,
            11.9,
            10.7,
            8.6,
            6.8,
            5.5,
            3.8,
            2.6,
            1.8,
            1.1,
            0.8,
            0.4
          ]
        }
      },
      "weather": {
        "temperature": 82.8,
        "wind_speed": 4.6,
        "wind_direction": "cross",
        "condition": "Forecast"
      },
      "park_factors": {
        "runs": 1.05,
        "lhb_ba": 1.0,
        "rhb_ba": 1.0,
        "lhb_hr": 1.29,
        "rhb_hr": 1.1,
        "bb": 1.0,
        "k": 1.0,
        "HR": 1.23,
        "1B": 1.0,
        "2B": 1.05,
        "3B": 0.92
      },
      "elo_home_rating": 1584,
      "elo_away_rating": 1481,
      "market_home_wp": 0.661,
      "market_away_wp": 0.339,
      "books_home": {
        "fanduel": -220,
        "draftkings": -219,
        "williamhill_us": -220,
        "bovada": -220,
        "betmgm": -220
      },
      "books_away": {
        "fanduel": 184,
        "draftkings": 178,
        "williamhill_us": 180,
        "bovada": 180,
        "betmgm": 180
      },
      "confidence": 1.0
    },
    {
      "away": "BAL",
      "home": "BOS",
      "away_pitcher": "Chris Bassitt",
      "home_pitcher": "Payton Tolle",
      "model_home_wp": 0.5093,
      "model_away_wp": 0.4907,
      "avg_total_runs": 9.36,
      "elo_home_wp": 0.4746,
      "sim_home_wp": 0.5439,
      "lineup_status": "projected",
      "home_lineup_names": [
        "Jarren Duran",
        "Ceddanne Rafaela",
        "Wilyer Abreu",
        "Willson Contreras",
        "Mickey Gasper",
        "Isiah Kiner-Falefa",
        "Marcelo Mayer",
        "Carlos Narv\u00e1ez",
        "Caleb Durbin"
      ],
      "away_lineup_names": [
        "Taylor Ward",
        "Gunnar Henderson",
        "Adley Rutschman",
        "Pete Alonso",
        "Samuel Basallo",
        "Coby Mayo",
        "Tyler O'Neill",
        "Leody Taveras",
        "Blaze Alexander"
      ],
      "sim_detail": {
        "avg_home_runs": 4.68,
        "avg_away_runs": 4.68,
        "std_total_runs": 4.39,
        "margin_distribution": {
          "labels": [
            -10,
            -9,
            -8,
            -7,
            -6,
            -5,
            -4,
            -3,
            -2,
            -1,
            0,
            1,
            2,
            3,
            4,
            5,
            6,
            7,
            8,
            9,
            10
          ],
          "freq": [
            0.8,
            1.0,
            1.6,
            2.2,
            2.9,
            4.2,
            5.7,
            7.5,
            9.4,
            11.8,
            0.0,
            14.3,
            10.4,
            8.2,
            6.1,
            4.2,
            3.2,
            2.0,
            1.2,
            0.8,
            0.5
          ]
        },
        "run_distribution": {
          "labels": [
            0,
            1,
            2,
            3,
            4,
            5,
            6,
            7,
            8,
            9,
            10,
            11,
            12,
            13,
            14,
            15
          ],
          "home_freq": [
            4.8,
            9.1,
            12.3,
            12.7,
            13.8,
            12.1,
            10.2,
            8.3,
            5.7,
            4.4,
            2.4,
            1.7,
            1.1,
            0.7,
            0.4,
            0.2
          ],
          "away_freq": [
            5.6,
            9.9,
            11.5,
            13.1,
            12.9,
            11.3,
            10.4,
            7.7,
            5.8,
            3.9,
            3.0,
            1.8,
            1.2,
            0.7,
            0.5,
            0.2
          ]
        }
      },
      "weather": {
        "temperature": 72.8,
        "wind_speed": 6.4,
        "wind_direction": "in",
        "condition": "Forecast"
      },
      "park_factors": {
        "runs": 1.05,
        "lhb_ba": 1.1,
        "rhb_ba": 1.0,
        "lhb_hr": 0.84,
        "rhb_hr": 0.88,
        "bb": 1.0,
        "k": 0.93,
        "HR": 0.86,
        "1B": 1.04,
        "2B": 1.1,
        "3B": 0.8
      },
      "elo_home_rating": 1497,
      "elo_away_rating": 1539,
      "market_home_wp": 0.569,
      "market_away_wp": 0.431,
      "books_home": {
        "fanduel": -142,
        "draftkings": -149,
        "williamhill_us": -145,
        "bovada": -142,
        "betmgm": -155
      },
      "books_away": {
        "fanduel": 120,
        "draftkings": 123,
        "williamhill_us": 122,
        "bovada": 119,
        "betmgm": 125
      },
      "confidence": 1.0
    },
    {
      "away": "CLE",
      "home": "NYY",
      "away_pitcher": "Gavin Williams",
      "home_pitcher": "Gerrit Cole",
      "model_home_wp": 0.5371,
      "model_away_wp": 0.4629,
      "avg_total_runs": 9.65,
      "elo_home_wp": 0.5122,
      "sim_home_wp": 0.562,
      "lineup_status": "projected",
      "home_lineup_names": [
        "Trent Grisham",
        "Ben Rice",
        "Aaron Judge",
        "Cody Bellinger",
        "Jazz Chisholm Jr.",
        "Paul Goldschmidt",
        "Ryan McMahon",
        "J.C. Escarra",
        "Jos\u00e9 Caballero"
      ],
      "away_lineup_names": [
        "Travis Bazzana",
        "Jos\u00e9 Ram\u00edrez",
        "Chase DeLauter",
        "Kyle Manzardo",
        "Angel Mart\u00ednez",
        "Daniel Schneemann",
        "Steven Kwan",
        "Patrick Bailey",
        "Brayan Rocchio"
      ],
      "sim_detail": {
        "avg_home_runs": 4.93,
        "avg_away_runs": 4.72,
        "std_total_runs": 4.44,
        "margin_distribution": {
          "labels": [
            -10,
            -9,
            -8,
            -7,
            -6,
            -5,
            -4,
            -3,
            -2,
            -1,
            0,
            1,
            2,
            3,
            4,
            5,
            6,
            7,
            8,
            9,
            10
          ],
          "freq": [
            0.8,
            0.9,
            1.3,
            2.2,
            3.1,
            3.8,
            5.6,
            7.3,
            8.8,
            11.6,
            0.0,
            14.1,
            10.8,
            8.4,
            6.2,
            4.8,
            3.1,
            2.0,
            1.5,
            1.1,
            0.8
          ]
        },
        "run_distribution": {
          "labels": [
            0,
            1,
            2,
            3,
            4,
            5,
            6,
            7,
            8,
            9,
            10,
            11,
            12,
            13,
            14,
            15
          ],
          "home_freq": [
            4.5,
            8.1,
            10.9,
            13.1,
            12.6,
            12.1,
            11.1,
            8.7,
            6.7,
            4.3,
            2.8,
            2.1,
            1.2,
            1.0,
            0.5,
            0.2
          ],
          "away_freq": [
            5.5,
            8.9,
            12.3,
            13.1,
            13.0,
            11.1,
            10.2,
            8.3,
            5.7,
            4.1,
            2.9,
            1.9,
            1.1,
            0.8,
            0.4,
            0.3
          ]
        }
      },
      "weather": {
        "temperature": 77.7,
        "wind_speed": 8.2,
        "wind_direction": "cross",
        "condition": "Forecast"
      },
      "park_factors": {
        "runs": 1.0,
        "lhb_ba": 1.0,
        "rhb_ba": 0.95,
        "lhb_hr": 1.17,
        "rhb_hr": 1.16,
        "bb": 1.0,
        "k": 1.0,
        "HR": 1.18,
        "1B": 0.97,
        "2B": 1.0,
        "3B": 0.81
      },
      "elo_home_rating": 1533,
      "elo_away_rating": 1548,
      "market_home_wp": 0.5927,
      "market_away_wp": 0.4073,
      "books_home": {
        "fanduel": -154,
        "draftkings": -163,
        "williamhill_us": -165,
        "bovada": -155,
        "betmgm": -165
      },
      "books_away": {
        "fanduel": 130,
        "draftkings": 135,
        "williamhill_us": 140,
        "bovada": 130,
        "betmgm": 135
      },
      "confidence": 1.0
    },
    {
      "away": "KCR",
      "home": "CIN",
      "away_pitcher": "Stephen Kolek",
      "home_pitcher": "Chase Burns",
      "model_home_wp": 0.6064,
      "model_away_wp": 0.3936,
      "avg_total_runs": 10.38,
      "elo_home_wp": 0.6993,
      "sim_home_wp": 0.5135,
      "lineup_status": "projected",
      "home_lineup_names": [
        "Blake Dunn",
        "JJ Bleday",
        "Sal Stewart",
        "Eugenio Su\u00e1rez",
        "Nathaniel Lowe",
        "Spencer Steer",
        "Tyler Stephenson",
        "Edwin Arroyo",
        "Matt McLain"
      ],
      "away_lineup_names": [
        "Carter Jensen",
        "Bobby Witt Jr.",
        "Vinnie Pasquantino",
        "Salvador Perez",
        "Jac Caglianone",
        "Isaac Collins",
        "Michael Massey",
        "Nick Loftin",
        "Kyle Isbel"
      ],
      "sim_detail": {
        "avg_home_runs": 5.02,
        "avg_away_runs": 5.37,
        "std_total_runs": 4.68,
        "margin_distribution": {
          "labels": [
            -10,
            -9,
            -8,
            -7,
            -6,
            -5,
            -4,
            -3,
            -2,
            -1,
            0,
            1,
            2,
            3,
            4,
            5,
            6,
            7,
            8,
            9,
            10
          ],
          "freq": [
            0.8,
            1.3,
            2.0,
            2.3,
            3.9,
            4.7,
            6.3,
            8.0,
            9.5,
            10.8,
            0.0,
            13.4,
            10.3,
            7.3,
            5.7,
            4.0,
            2.9,
            1.8,
            1.1,
            0.9,
            0.6
          ]
        },
        "run_distribution": {
          "labels": [
            0,
            1,
            2,
            3,
            4,
            5,
            6,
            7,
            8,
            9,
            10,
            11,
            12,
            13,
            14,
            15
          ],
          "home_freq": [
            4.3,
            7.1,
            11.3,
            12.7,
            12.8,
            12.0,
            11.1,
            8.7,
            6.5,
            5.0,
            3.1,
            2.0,
            1.3,
            0.8,
            0.4,
            0.3
          ],
          "away_freq": [
            3.6,
            7.2,
            10.0,
            11.1,
            12.7,
            12.0,
            10.6,
            9.2,
            7.1,
            5.5,
            3.4,
            2.8,
            1.7,
            1.1,
            0.8,
            0.4
          ]
        }
      },
      "weather": {
        "temperature": 81.4,
        "wind_speed": 4.6,
        "wind_direction": "cross",
        "condition": "Forecast"
      },
      "park_factors": {
        "runs": 1.05,
        "lhb_ba": 1.0,
        "rhb_ba": 1.0,
        "lhb_hr": 1.35,
        "rhb_hr": 1.26,
        "bb": 1.0,
        "k": 1.0,
        "HR": 1.33,
        "1B": 1.0,
        "2B": 1.07,
        "3B": 1.0
      },
      "elo_home_rating": 1483,
      "elo_away_rating": 1360,
      "market_home_wp": 0.5872,
      "market_away_wp": 0.4128,
      "books_home": {
        "draftkings": -157,
        "williamhill_us": -155,
        "bovada": -160,
        "betmgm": -155,
        "fanduel": -158
      },
      "books_away": {
        "draftkings": 130,
        "williamhill_us": 130,
        "bovada": 134,
        "betmgm": 125,
        "fanduel": 134
      },
      "confidence": 1.0
    },
    {
      "away": "TOR",
      "home": "ATL",
      "away_pitcher": "Patrick Corbin",
      "home_pitcher": "Grant Holmes",
      "model_home_wp": 0.61,
      "model_away_wp": 0.39,
      "avg_total_runs": 9.14,
      "elo_home_wp": 0.6839,
      "sim_home_wp": 0.5362,
      "lineup_status": "projected",
      "home_lineup_names": [
        "Ronald Acu\u00f1a Jr.",
        "Michael Harris II",
        "Matt Olson",
        "Ozzie Albies",
        "Mauricio Dub\u00f3n",
        "Austin Riley",
        "Jorge Mateo",
        "Ha-Seong Kim",
        "Chadwick Tromp"
      ],
      "away_lineup_names": [
        "George Springer",
        "Nathan Lukes",
        "Vladimir Guerrero Jr.",
        "Daulton Varsho",
        "Ernie Clement",
        "Yohendrick Pi\u00f1ango",
        "Kazuma Okamoto",
        "Andr\u00e9s Gim\u00e9nez",
        "Brandon Valenzuela"
      ],
      "sim_detail": {
        "avg_home_runs": 4.51,
        "avg_away_runs": 4.63,
        "std_total_runs": 4.35,
        "margin_distribution": {
          "labels": [
            -10,
            -9,
            -8,
            -7,
            -6,
            -5,
            -4,
            -3,
            -2,
            -1,
            0,
            1,
            2,
            3,
            4,
            5,
            6,
            7,
            8,
            9,
            10
          ],
          "freq": [
            0.7,
            0.9,
            1.7,
            2.3,
            3.2,
            4.3,
            5.9,
            7.8,
            9.2,
            11.8,
            0.0,
            14.2,
            11.5,
            8.1,
            5.8,
            3.8,
            2.7,
            1.8,
            1.2,
            0.8,
            0.5
          ]
        },
        "run_distribution": {
          "labels": [
            0,
            1,
            2,
            3,
            4,
            5,
            6,
            7,
            8,
            9,
            10,
            11,
            12,
            13,
            14,
            15
          ],
          "home_freq": [
            5.7,
            9.2,
            12.6,
            14.0,
            13.8,
            11.7,
            9.8,
            8.1,
            5.6,
            3.4,
            2.4,
            1.6,
            0.9,
            0.6,
            0.3,
            0.1
          ],
          "away_freq": [
            6.0,
            9.6,
            12.0,
            13.3,
            13.3,
            11.3,
            9.7,
            7.5,
            5.9,
            4.0,
            2.9,
            1.8,
            1.1,
            0.7,
            0.5,
            0.2
          ]
        }
      },
      "weather": {
        "temperature": 75.7,
        "wind_speed": 8.4,
        "wind_direction": "cross",
        "condition": "Forecast"
      },
      "park_factors": {
        "runs": 1.0,
        "lhb_ba": 1.0,
        "rhb_ba": 1.0,
        "lhb_hr": 1.0,
        "rhb_hr": 0.93,
        "bb": 1.0,
        "k": 1.0,
        "HR": 0.98,
        "1B": 1.0,
        "2B": 1.03,
        "3B": 0.96
      },
      "elo_home_rating": 1620,
      "elo_away_rating": 1510,
      "market_home_wp": 0.569,
      "market_away_wp": 0.431,
      "books_home": {
        "fanduel": -142,
        "draftkings": -149,
        "williamhill_us": -145,
        "bovada": -142,
        "betmgm": -150
      },
      "books_away": {
        "fanduel": 120,
        "draftkings": 123,
        "williamhill_us": 122,
        "bovada": 119,
        "betmgm": 125
      },
      "confidence": 1.0
    },
    {
      "away": "SFG",
      "home": "MIL",
      "away_pitcher": "Logan Webb",
      "home_pitcher": "",
      "status": "lineups_pending",
      "lineup_status": "pending"
    },
    {
      "away": "TEX",
      "home": "STL",
      "away_pitcher": "MacKenzie Gore",
      "home_pitcher": "Andre Pallante",
      "model_home_wp": 0.4864,
      "model_away_wp": 0.5136,
      "avg_total_runs": 9.1,
      "elo_home_wp": 0.4644,
      "sim_home_wp": 0.5084,
      "lineup_status": "projected",
      "home_lineup_names": [
        "JJ Wetherholt",
        "Iv\u00e1n Herrera",
        "Jordan Walker",
        "Nelson Vel\u00e1zquez",
        "Alec Burleson",
        "Masyn Winn",
        "Jos\u00e9 Ferm\u00edn",
        "Thomas Saggese",
        "Victor Scott II"
      ],
      "away_lineup_names": [
        "Joc Pederson",
        "Josh Jung",
        "Brandon Nimmo",
        "Jake Burger",
        "Ezequiel Duran",
        "Alejandro Osuna",
        "Evan Carter",
        "Danny Jansen",
        "Nicky Lopez"
      ],
      "sim_detail": {
        "avg_home_runs": 4.38,
        "avg_away_runs": 4.73,
        "std_total_runs": 4.4,
        "margin_distribution": {
          "labels": [
            -10,
            -9,
            -8,
            -7,
            -6,
            -5,
            -4,
            -3,
            -2,
            -1,
            0,
            1,
            2,
            3,
            4,
            5,
            6,
            7,
            8,
            9,
            10
          ],
          "freq": [
            0.8,
            1.1,
            1.8,
            2.3,
            3.4,
            4.5,
            6.2,
            8.2,
            10.0,
            12.3,
            0.0,
            14.2,
            10.1,
            8.0,
            5.2,
            3.9,
            2.7,
            1.7,
            1.0,
            0.6,
            0.4
          ]
        },
        "run_distribution": {
          "labels": [
            0,
            1,
            2,
            3,
            4,
            5,
            6,
            7,
            8,
            9,
            10,
            11,
            12,
            13,
            14,
            15
          ],
          "home_freq": [
            5.9,
            9.9,
            13.0,
            14.1,
            13.7,
            12.7,
            9.4,
            7.3,
            5.1,
            3.3,
            2.2,
            1.4,
            0.9,
            0.4,
            0.3,
            0.1
          ],
          "away_freq": [
            5.5,
            9.2,
            12.2,
            13.4,
            12.7,
            11.6,
            9.8,
            7.4,
            5.9,
            4.3,
            2.8,
            1.9,
            1.1,
            0.9,
            0.4,
            0.3
          ]
        }
      },
      "weather": {
        "temperature": 81.8,
        "wind_speed": 5.9,
        "wind_direction": "in",
        "condition": "Forecast"
      },
      "park_factors": {
        "runs": 1.0,
        "lhb_ba": 1.0,
        "rhb_ba": 1.0,
        "lhb_hr": 0.95,
        "rhb_hr": 0.82,
        "bb": 1.0,
        "k": 0.93,
        "HR": 0.91,
        "1B": 1.0,
        "2B": 1.03,
        "3B": 0.97
      },
      "elo_home_rating": 1458,
      "elo_away_rating": 1507,
      "market_home_wp": 0.5068,
      "market_away_wp": 0.4932,
      "books_home": {
        "fanduel": -110,
        "draftkings": -115,
        "williamhill_us": -115,
        "bovada": -112,
        "betmgm": -115
      },
      "books_away": {
        "fanduel": -106,
        "draftkings": -104,
        "williamhill_us": -105,
        "bovada": -108,
        "betmgm": -105
      },
      "confidence": 0.959
    },
    {
      "away": "Athletics",
      "home": "CHC",
      "away_pitcher": "Jeffrey Springs",
      "home_pitcher": "Colin Rea",
      "model_home_wp": 0.5292,
      "model_away_wp": 0.4708,
      "avg_total_runs": 9.09,
      "elo_home_wp": 0.5291,
      "sim_home_wp": 0.5294,
      "lineup_status": "projected",
      "home_lineup_names": [
        "Nico Hoerner",
        "Alex Bregman",
        "Ian Happ",
        "Seiya Suzuki",
        "Carson Kelly",
        "Michael Busch",
        "Dansby Swanson",
        "Miguel Amaya",
        "Pete Crow-Armstrong"
      ],
      "away_lineup_names": [
        "Carlos Cortes",
        "Nick Kurtz",
        "Shea Langeliers",
        "Tyler Soderstrom",
        "Jonah Heim",
        "Henry Bolte",
        "Jeff McNeil",
        "Zack Gelof",
        "Darell Hernaiz"
      ],
      "sim_detail": {
        "avg_home_runs": 4.52,
        "avg_away_runs": 4.58,
        "std_total_runs": 4.45,
        "margin_distribution": {
          "labels": [
            -10,
            -9,
            -8,
            -7,
            -6,
            -5,
            -4,
            -3,
            -2,
            -1,
            0,
            1,
            2,
            3,
            4,
            5,
            6,
            7,
            8,
            9,
            10
          ],
          "freq": [
            0.6,
            0.8,
            1.3,
            2.0,
            3.1,
            4.3,
            6.1,
            7.4,
            10.2,
            12.8,
            0.0,
            14.2,
            11.0,
            7.6,
            5.5,
            3.9,
            2.8,
            1.9,
            1.3,
            1.0,
            0.7
          ]
        },
        "run_distribution": {
          "labels": [
            0,
            1,
            2,
            3,
            4,
            5,
            6,
            7,
            8,
            9,
            10,
            11,
            12,
            13,
            14,
            15
          ],
          "home_freq": [
            5.5,
            9.5,
            12.9,
            13.8,
            13.9,
            12.0,
            9.4,
            7.5,
            5.4,
            3.6,
            2.4,
            1.5,
            0.9,
            0.7,
            0.4,
            0.2
          ],
          "away_freq": [
            6.3,
            9.9,
            12.5,
            13.7,
            12.1,
            11.6,
            9.6,
            7.3,
            5.6,
            4.1,
            2.9,
            1.4,
            1.1,
            0.7,
            0.5,
            0.3
          ]
        }
      },
      "weather": {
        "temperature": 73.3,
        "wind_speed": 7.8,
        "wind_direction": "cross",
        "condition": "Forecast"
      },
      "park_factors": {
        "runs": 0.92,
        "lhb_ba": 1.0,
        "rhb_ba": 0.94,
        "lhb_hr": 0.86,
        "rhb_hr": 1.0,
        "bb": 1.0,
        "k": 1.06,
        "HR": 0.93,
        "1B": 0.97,
        "2B": 1.01,
        "3B": 1.0
      },
      "elo_home_rating": 1442,
      "elo_away_rating": 1446,
      "market_home_wp": 0.5298,
      "market_away_wp": 0.4702,
      "books_home": {
        "fanduel": -122,
        "draftkings": -125,
        "williamhill_us": -125,
        "bovada": -123,
        "betmgm": -130
      },
      "books_away": {
        "fanduel": 104,
        "draftkings": 104,
        "williamhill_us": 105,
        "bovada": 103,
        "betmgm": 105
      },
      "confidence": 1.0
    },
    {
      "away": "PIT",
      "home": "HOU",
      "away_pitcher": "Paul Skenes",
      "home_pitcher": "Spencer Arrighetti",
      "model_home_wp": 0.4948,
      "model_away_wp": 0.5052,
      "avg_total_runs": 9.0,
      "elo_home_wp": 0.4867,
      "sim_home_wp": 0.5029,
      "lineup_status": "projected",
      "home_lineup_names": [
        "Jeremy Pe\u00f1a",
        "Yordan Alvarez",
        "Christian Walker",
        "Isaac Paredes",
        "Taylor Trammell",
        "Cam Smith",
        "Jake Meyers",
        "Brice Matthews",
        "C\u00e9sar Salazar"
      ],
      "away_lineup_names": [
        "Spencer Horwitz",
        "Brandon Lowe",
        "Bryan Reynolds",
        "Ryan O'Hearn",
        "Nick Gonzales",
        "Oneil Cruz",
        "Jared Triolo",
        "Jake Mangum",
        "Henry Davis"
      ],
      "sim_detail": {
        "avg_home_runs": 4.28,
        "avg_away_runs": 4.72,
        "std_total_runs": 4.31,
        "margin_distribution": {
          "labels": [
            -10,
            -9,
            -8,
            -7,
            -6,
            -5,
            -4,
            -3,
            -2,
            -1,
            0,
            1,
            2,
            3,
            4,
            5,
            6,
            7,
            8,
            9,
            10
          ],
          "freq": [
            0.7,
            1.3,
            1.6,
            2.6,
            3.5,
            4.6,
            6.3,
            8.2,
            9.9,
            12.3,
            0.0,
            14.2,
            11.0,
            7.2,
            5.4,
            3.4,
            2.4,
            1.5,
            0.9,
            0.7,
            0.4
          ]
        },
        "run_distribution": {
          "labels": [
            0,
            1,
            2,
            3,
            4,
            5,
            6,
            7,
            8,
            9,
            10,
            11,
            12,
            13,
            14,
            15
          ],
          "home_freq": [
            6.5,
            11.0,
            12.9,
            13.8,
            14.1,
            11.9,
            9.0,
            7.2,
            4.9,
            3.4,
            2.0,
            1.3,
            0.8,
            0.5,
            0.4,
            0.1
          ],
          "away_freq": [
            5.5,
            8.9,
            11.7,
            13.5,
            13.3,
            11.7,
            9.5,
            8.1,
            6.1,
            4.2,
            2.6,
            1.9,
            1.2,
            0.8,
            0.3,
            0.3
          ]
        }
      },
      "weather": {
        "condition": "Roof Closed"
      },
      "park_factors": {
        "runs": 1.0,
        "lhb_ba": 1.0,
        "rhb_ba": 1.0,
        "lhb_hr": 1.0,
        "rhb_hr": 1.07,
        "bb": 1.0,
        "k": 1.05,
        "HR": 1.04,
        "1B": 1.0,
        "2B": 1.01,
        "3B": 0.9
      },
      "elo_home_rating": 1507,
      "elo_away_rating": 1540,
      "market_home_wp": 0.4077,
      "market_away_wp": 0.5923,
      "books_home": {
        "fanduel": 138,
        "draftkings": 129,
        "williamhill_us": 130,
        "bovada": 139,
        "betmgm": 125
      },
      "books_away": {
        "fanduel": -164,
        "draftkings": -156,
        "williamhill_us": -155,
        "bovada": -165,
        "betmgm": -155
      },
      "confidence": 1.0,
      "pick": "HOU ML",
      "edge_pct": 7.8,
      "odds": "+139",
      "kelly_fraction": 0.0291,
      "explanation": "Nobody wants to bet against Paul Skenes, which is exactly why this number exists. The market is pricing him like he can't be touched, but Houston runs out a righty-heavy order that happens to be his weakest split, and Alvarez is the kind of left-handed bat who turns a quiet start into a loud one. Arrighetti is the obvious problem on the other side, but the Pirates lineup isn't built to make him pay the way the projection suggests, and a roof-closed game tends to compress variance toward the coin flip our numbers already see. At +139 on a game we make closer to a pick'em, you're getting paid to take the side everyone is talking themselves out of."
    },
    {
      "away": "COL",
      "home": "LAA",
      "away_pitcher": "Michael Lorenzen",
      "home_pitcher": "Walbert Ure\u00f1a",
      "status": "lineups_pending",
      "lineup_status": "pending"
    },
    {
      "away": "LAD",
      "home": "ARI",
      "away_pitcher": "Shohei Ohtani",
      "home_pitcher": "Zac Gallen",
      "model_home_wp": 0.4154,
      "model_away_wp": 0.5846,
      "avg_total_runs": 9.99,
      "elo_home_wp": 0.3621,
      "sim_home_wp": 0.4688,
      "lineup_status": "projected",
      "home_lineup_names": [
        "Ketel Marte",
        "Corbin Carroll",
        "Geraldo Perdomo",
        "Nolan Arenado",
        "Pavin Smith",
        "Gabriel Moreno",
        "Ildemaro Vargas",
        "Ryan Waldschmidt",
        "Tommy Troy"
      ],
      "away_lineup_names": [
        "Shohei Ohtani",
        "Andy Pages",
        "Freddie Freeman",
        "Mookie Betts",
        "Kyle Tucker",
        "Max Muncy",
        "Will Smith",
        "Alex Call",
        "Alex Freeland"
      ],
      "sim_detail": {
        "avg_home_runs": 4.55,
        "avg_away_runs": 5.43,
        "std_total_runs": 4.72,
        "margin_distribution": {
          "labels": [
            -10,
            -9,
            -8,
            -7,
            -6,
            -5,
            -4,
            -3,
            -2,
            -1,
            0,
            1,
            2,
            3,
            4,
            5,
            6,
            7,
            8,
            9,
            10
          ],
          "freq": [
            1.1,
            1.7,
            2.5,
            3.4,
            4.1,
            5.5,
            7.0,
            7.9,
            9.6,
            11.0,
            0.0,
            13.3,
            9.5,
            6.7,
            5.0,
            3.4,
            2.5,
            1.4,
            1.0,
            0.7,
            0.5
          ]
        },
        "run_distribution": {
          "labels": [
            0,
            1,
            2,
            3,
            4,
            5,
            6,
            7,
            8,
            9,
            10,
            11,
            12,
            13,
            14,
            15
          ],
          "home_freq": [
            5.9,
            9.6,
            12.3,
            13.6,
            13.4,
            12.1,
            9.4,
            7.5,
            5.5,
            3.9,
            2.6,
            1.7,
            1.1,
            0.6,
            0.3,
            0.2
          ],
          "away_freq": [
            3.9,
            7.4,
            10.1,
            11.8,
            11.2,
            11.7,
            10.2,
            8.7,
            7.2,
            5.2,
            4.0,
            3.2,
            1.9,
            1.3,
            0.9,
            0.6
          ]
        }
      },
      "weather": {
        "condition": "Roof Closed"
      },
      "park_factors": {
        "runs": 1.0,
        "lhb_ba": 1.0,
        "rhb_ba": 1.0,
        "lhb_hr": 0.72,
        "rhb_hr": 0.87,
        "bb": 1.0,
        "k": 1.0,
        "HR": 0.8,
        "1B": 1.01,
        "2B": 1.02,
        "3B": 0.95
      },
      "elo_home_rating": 1536,
      "elo_away_rating": 1659,
      "market_home_wp": 0.3629,
      "market_away_wp": 0.6371,
      "books_home": {
        "fanduel": 168,
        "draftkings": 158,
        "williamhill_us": 158,
        "bovada": 167,
        "betmgm": 154
      },
      "books_away": {
        "fanduel": -200,
        "draftkings": -193,
        "williamhill_us": -190,
        "bovada": -204,
        "betmgm": -190
      },
      "confidence": 1.0
    }
  ],
  "picks": [
    {
      "pick": "SDP +1.5",
      "side": "away",
      "team": "SDP",
      "opponent": "PHI",
      "edge_pct": 8.0,
      "model_prob": 0.607,
      "confidence": 1.0,
      "odds": "-110",
      "kelly_fraction": 0.0389,
      "wager": 3170.19,
      "explanation": "Sanchez against a righty-heavy Padres lineup is a tougher ask than the price suggests, because his platoon split flips hard when lefties aren't in the box. Tatis and Machado are exactly the kind of right-handed thump that has tagged him for a .289 xwOBA this year, and Buehler, for all his command issues, only needs to keep this within a run to cash. The sim has it landing inside a single tally, which is the whole reason the runline exists at this number. Getting a plus-the-hook at -110 on a one-score game is the math doing the heavy lifting.",
      "type": "run_line",
      "sportsbook_odds": {
        "fanduel": -110,
        "draftkings": -122,
        "williamhill_us": -125,
        "bovada": -125,
        "betmgm": -125
      },
      "lineup_status": "projected"
    },
    {
      "pick": "HOU ML",
      "side": "home",
      "team": "HOU",
      "opponent": "PIT",
      "edge_pct": 7.8,
      "model_prob": 0.495,
      "confidence": 1.0,
      "odds": "+139",
      "kelly_fraction": 0.0291,
      "wager": 2374.43,
      "explanation": "Nobody wants to bet against Paul Skenes, which is exactly why this number exists. The market is pricing him like he can't be touched, but Houston runs out a righty-heavy order that happens to be his weakest split, and Alvarez is the kind of left-handed bat who turns a quiet start into a loud one. Arrighetti is the obvious problem on the other side, but the Pirates lineup isn't built to make him pay the way the projection suggests, and a roof-closed game tends to compress variance toward the coin flip our numbers already see. At +139 on a game we make closer to a pick'em, you're getting paid to take the side everyone is talking themselves out of.",
      "type": "moneyline",
      "sportsbook_odds": {
        "fanduel": 138,
        "draftkings": 129,
        "williamhill_us": 130,
        "bovada": 139,
        "betmgm": 125
      },
      "lineup_status": "projected"
    }
  ],
  "bankroll": {
    "current": 81600.72,
    "today_wagered": 5544.62
  }
}