{"game_id":{"0":"891e69457152c080ffcc21c7d270d496","1":"4c66d2e13ce50dd60d19e8cff8bbd7c8","2":"c36bdb8231822ee0f1da32b6be40b9b0","3":"05b5c7cee311b071b85433bf42dc4612","4":"c679aca8a08df633e4d70c359217ffe5","5":"5b5ca06821ecfe2cbf46026575ed9263","6":"928d36763fd31061810699e36df3bba8","7":"375d31006805a62964445dd208379b2b","8":"060e554031da942cb986e3f4a4934693","9":"e1a00a3014c67a9c52882049b063f78a","10":"07281b73eef3ffc23544bbe5a9393d44","11":"c00c26980a4f67d0037ac7fd8a3dd15b","12":"cd7e74e983be115f2ccb417ccb4f845d","13":"715a197e2d41a434a760c22ec0a823c5","14":"325a216ed291897f85ab8c9b49ebd33d"},"commence_time":{"0":"2026-06-10T17:11:00Z","1":"2026-06-10T17:11:00Z","2":"2026-06-10T19:46:00Z","3":"2026-06-10T20:11:00Z","4":"2026-06-10T22:36:00Z","5":"2026-06-10T22:41:00Z","6":"2026-06-10T22:41:00Z","7":"2026-06-10T22:41:00Z","8":"2026-06-10T23:08:00Z","9":"2026-06-10T23:11:00Z","10":"2026-06-10T23:41:00Z","11":"2026-06-10T23:41:00Z","12":"2026-06-11T00:41:00Z","13":"2026-06-11T01:06:00Z","14":"2026-06-11T01:39:00Z"},"home_team":{"0":"Tampa Bay Rays","1":"Cleveland Guardians","2":"San Francisco Giants","3":"San Diego Padres","4":"Baltimore Orioles","5":"Miami Marlins","6":"Detroit Tigers","7":"Pittsburgh Pirates","8":"Toronto Blue Jays","9":"New York Mets","10":"Chicago White Sox","11":"Kansas City Royals","12":"Colorado Rockies","13":"Athletics","14":"Los Angeles Angels"},"away_team":{"0":"Boston Red Sox","1":"New York Yankees","2":"Washington Nationals","3":"Cincinnati Reds","4":"Seattle Mariners","5":"Arizona Diamondbacks","6":"Minnesota Twins","7":"Los Angeles Dodgers","8":"Philadelphia Phillies","9":"St. Louis Cardinals","10":"Atlanta Braves","11":"Texas Rangers","12":"Chicago Cubs","13":"Milwaukee Brewers","14":"Houston Astros"},"best_home_odds":{"0":-149,"1":-118,"2":-117,"3":-164,"4":105,"5":-102,"6":-170,"7":176,"8":130,"9":-132,"10":130,"11":104,"12":145,"13":-109,"14":-119},"best_away_odds":{"0":130,"1":100,"2":102,"3":143,"4":-122,"5":-112,"6":146,"7":-200,"8":-145,"9":115,"10":-150,"11":-120,"12":-170,"13":-104,"14":102},"best_home_book":{"0":"bovada","1":"fanduel","2":"bovada","3":"fanduel","4":"williamhill_us","5":"fanduel","6":"williamhill_us","7":"bovada","8":"williamhill_us","9":"fanduel","10":"fanduel","11":"fanduel","12":"betmgm","13":"draftkings","14":"bovada"},"best_away_book":{"0":"fanduel","1":"fanduel","2":"fanduel","3":"williamhill_us","4":"fanduel","5":"draftkings","6":"fanduel","7":"betmgm","8":"bovada","9":"williamhill_us","10":"draftkings","11":"williamhill_us","12":"williamhill_us","13":"fanduel","14":"fanduel"},"home_implied_prob":{"0":0.5983935743,"1":0.5412844037,"2":0.5391705069,"3":0.6212121212,"4":0.487804878,"5":0.504950495,"6":0.6296296296,"7":0.3623188406,"8":0.4347826087,"9":0.5689655172,"10":0.4347826087,"11":0.4901960784,"12":0.4081632653,"13":0.5215311005,"14":0.5433789954},"away_implied_prob":{"0":0.4347826087,"1":0.5,"2":0.495049505,"3":0.4115226337,"4":0.5495495495,"5":0.5283018868,"6":0.406504065,"7":0.6666666667,"8":0.5918367347,"9":0.4651162791,"10":0.6,"11":0.5454545455,"12":0.6296296296,"13":0.5098039216,"14":0.495049505},"home_no_vig_prob":{"0":0.5791786378,"1":0.5198237885,"2":0.5213305687,"3":0.6015214635,"4":0.4702393561,"5":0.4887000542,"6":0.6076721883,"7":0.3521126761,"8":0.4235090752,"9":0.550213261,"10":0.4201680672,"11":0.4733218589,"12":0.3932993445,"13":0.5056854362,"14":0.523270495},"away_no_vig_prob":{"0":0.4208213622,"1":0.4801762115,"2":0.4786694313,"3":0.3984785365,"4":0.5297606439,"5":0.5112999458,"6":0.3923278117,"7":0.6478873239,"8":0.5764909248,"9":0.449786739,"10":0.5798319328,"11":0.5266781411,"12":0.6067006555,"13":0.4943145638,"14":0.476729505},"pinnacle_home":{"0":null,"1":null,"2":null,"3":null,"4":null,"5":null,"6":null,"7":null,"8":null,"9":null,"10":null,"11":null,"12":null,"13":null,"14":null},"pinnacle_away":{"0":null,"1":null,"2":null,"3":null,"4":null,"5":null,"6":null,"7":null,"8":null,"9":null,"10":null,"11":null,"12":null,"13":null,"14":null},"vig":{"0":0.033176183,"1":0.0412844037,"2":0.0342200119,"3":0.032734755,"4":0.0373544276,"5":0.0332523818,"6":0.0361336947,"7":0.0289855072,"8":0.0266193434,"9":0.0340817963,"10":0.0347826087,"11":0.0356506239,"12":0.0377928949,"13":0.031335022,"14":0.0384285004},"books_home":{"0":{"fanduel":-154,"williamhill_us":-155,"betmgm":-150,"draftkings":-157,"bovada":-149},"1":{"fanduel":-118,"williamhill_us":-120,"draftkings":-120,"bovada":-118,"betmgm":-120},"2":{"fanduel":-120,"williamhill_us":-120,"draftkings":-120,"bovada":-117,"betmgm":-120},"3":{"fanduel":-164,"williamhill_us":-170,"draftkings":-168,"bovada":-168,"betmgm":-170},"4":{"fanduel":104,"williamhill_us":105,"draftkings":104,"bovada":103,"betmgm":105},"5":{"fanduel":-102,"williamhill_us":-105,"draftkings":-107,"bovada":-105,"betmgm":-105},"6":{"fanduel":-174,"draftkings":-175,"williamhill_us":-170,"bovada":-177,"betmgm":-175},"7":{"fanduel":172,"williamhill_us":170,"draftkings":169,"bovada":176,"betmgm":165},"8":{"fanduel":128,"williamhill_us":130,"draftkings":123,"bovada":122,"betmgm":125},"9":{"fanduel":-132,"williamhill_us":-135,"draftkings":-136,"bovada":-135,"betmgm":-135},"10":{"fanduel":130,"draftkings":125,"williamhill_us":130,"bovada":127,"betmgm":125},"11":{"fanduel":104,"williamhill_us":100,"draftkings":102,"bovada":104,"betmgm":100},"12":{"fanduel":144,"williamhill_us":143,"draftkings":144,"bovada":141,"betmgm":145},"13":{"fanduel":-112,"draftkings":-109,"williamhill_us":-110,"bovada":-110,"betmgm":-110},"14":{"fanduel":-120,"williamhill_us":-120,"draftkings":-122,"bovada":-119,"betmgm":-120}},"books_away":{"0":{"fanduel":130,"williamhill_us":130,"betmgm":125,"draftkings":130,"bovada":125},"1":{"fanduel":100,"williamhill_us":100,"draftkings":-101,"bovada":-102,"betmgm":100},"2":{"fanduel":102,"williamhill_us":100,"draftkings":-101,"bovada":-103,"betmgm":100},"3":{"fanduel":138,"williamhill_us":143,"draftkings":139,"bovada":140,"betmgm":140},"4":{"fanduel":-122,"williamhill_us":-125,"draftkings":-125,"bovada":-123,"betmgm":-125},"5":{"fanduel":-116,"williamhill_us":-115,"draftkings":-112,"bovada":-115,"betmgm":-115},"6":{"fanduel":146,"draftkings":144,"williamhill_us":143,"bovada":145,"betmgm":145},"7":{"fanduel":-205,"williamhill_us":-205,"draftkings":-207,"bovada":-216,"betmgm":-200},"8":{"fanduel":-152,"williamhill_us":-155,"draftkings":-149,"bovada":-145,"betmgm":-155},"9":{"fanduel":112,"williamhill_us":115,"draftkings":113,"bovada":113,"betmgm":110},"10":{"fanduel":-154,"draftkings":-150,"williamhill_us":-155,"bovada":-152,"betmgm":-155},"11":{"fanduel":-122,"williamhill_us":-120,"draftkings":-123,"bovada":-124,"betmgm":-120},"12":{"fanduel":-172,"williamhill_us":-170,"draftkings":-175,"bovada":-170,"betmgm":-175},"13":{"fanduel":-104,"draftkings":-110,"williamhill_us":-110,"bovada":-110,"betmgm":-110},"14":{"fanduel":102,"williamhill_us":100,"draftkings":102,"bovada":-101,"betmgm":100}}}